MANIFEST.in
runner
setup.cfg
setup.py
HotRC.egg-info/PKG-INFO
HotRC.egg-info/SOURCES.txt
HotRC.egg-info/dependency_links.txt
HotRC.egg-info/requires.txt
HotRC.egg-info/top_level.txt
hotrc/__init__.py
hotrc/hotrc.py
hotrc/info
hotrc/path.sh
hotrc/reload.sh
hotrc/unalias.sh
hotrc/__pycache__/__init__.cpython-35.pyc
hotrc/__pycache__/hotrc.cpython-35.pyc
tests/__init__.py
tests/test_hotrc.py