Metadata-Version: 1.1
Name: HotRC
Version: 0.2.1
Summary: A command line tool for managing aliases in your .bashrc file.
Home-page: https://github.com/konstantinfarrell/hotrc
Author: Konstantin Farrell
Author-email: konstantinfarrell@gmail.com
License: MIT
Platform: UNKNOWN
Classifier: Development Status :: 3 - Alpha
Classifier: Environment :: Console
Classifier: Intended Audience :: Developers
Classifier: Intended Audience :: System Administrators
Classifier: License :: OSI Approved :: MIT License
Classifier: Programming Language :: Python :: 3
Classifier: Topic :: Utilities
